AUTHORS.rst
CONTRIBUTING.rst
HISTORY.rst
LICENSE
MANIFEST.in
README.rst
setup.cfg
setup.py
bin/popgen_run
popgen/__init__.py
popgen/config.py
popgen/data.py
popgen/draw.py
popgen/ipf.py
popgen/output.py
popgen/project.py
popgen/reweighting.py
popgen.egg-info/PKG-INFO
popgen.egg-info/SOURCES.txt
popgen.egg-info/dependency_links.txt
popgen.egg-info/not-zip-safe
popgen.egg-info/requires.txt
popgen.egg-info/top_level.txt
test/test_popgen.py