Metadata-Version: 1.1
Name: popgen
Version: 2.0b2
Summary: Synthetic Population Generator 2.0
Home-page: https://github.com/foss-transportationmodeling/popgen
Author: Karthik Konduri
Author-email: karthik.charan@gmail.com
License: Apache License 2.0
Keywords: popgen
Platform: UNKNOWN
Classifier: Development Status :: 4 - Beta
Classifier: Intended Audience :: Developers
Classifier: License :: OSI Approved :: Apache Software License
Classifier: Natural Language :: English
Classifier: Programming Language :: Python :: 2.7
Classifier: Operating System :: OS Independent
